Metadata-Version: 2.1
Name: array_api_strict
Version: 2.4.1
Summary: A strict, minimal implementation of the Python array API standard.
Author: Consortium for Python Data API Standards
License: Copyright (c) 2021-2024, NumPy Developers, Consortium for Python Data API Standards
Project-URL: Homepage, https://data-apis.org/array-api-strict/
Project-URL: Repository, https://github.com/data-apis/array-api-strict
Classifier: Programming Language :: Python :: 3
Classifier: Programming Language :: Python :: 3.10
Classifier: Programming Language :: Python :: 3.11
Classifier: Programming Language :: Python :: 3.12
Classifier: Programming Language :: Python :: 3.13
Classifier: License :: OSI Approved :: BSD License
Classifier: Operating System :: OS Independent
Requires-Python: >=3.10
License-File: LICENSE
Requires-Dist: numpy
